cfg_param_wrapper/__init__.py
cfg_param_wrapper/argparse_config.py
cfg_param_wrapper/cfg_dict.py
cfg_param_wrapper/function_config_wrapper.py
cfg_param_wrapper/save_handlers.py
cfg_param_wrapper-1.0.1.dist-info/LICENSE
cfg_param_wrapper-1.0.1.dist-info/METADATA
cfg_param_wrapper-1.0.1.dist-info/WHEEL
cfg_param_wrapper-1.0.1.dist-info/top_level.txt
cfg_param_wrapper-1.0.1.dist-info/RECORD
