Metadata-Version: 2.1
Name: cfg-param-wrapper
Version: 1.0.1
Summary: A package designed to simplify defaults.
Author-email: Zeptofine <zeptofine@gmail.com>
Project-URL: Homepage, https://github.com/zeptofine/cfg-argparser
Project-URL: Bug Tracker, https://github.com/zeptofine/cfg-argparser/issues
Classifier: Programming Language :: Python :: 3
Classifier: Programming Language :: Python :: 3.6
Classifier: Programming Language :: Python :: 3.7
Classifier: Programming Language :: Python :: 3.8
Classifier: Programming Language :: Python :: 3.9
Classifier: Programming Language :: Python :: 3.10
Classifier: Programming Language :: Python :: 3.11
Classifier: License :: OSI Approved :: MIT License
Classifier: Operating System :: OS Independent
License-File: LICENSE
Requires-Dist: toml
Provides-Extra: typer
Requires-Dist: typer[all] ; extra == 'typer'
